bkstorages/__init__.py
bkstorages/backends/__init__.py
bkstorages/backends/bkrepo.py
bkstorages/backends/rgw.py
bkstorages/exceptions.py
bkstorages/utils.py
bkstorages-2.0.3.dist-info/METADATA
bkstorages-2.0.3.dist-info/WHEEL
bkstorages-2.0.3.dist-info/RECORD
