Metadata-Version: 2.3
Name: bkstorages
Version: 2.0.3
Summary: File storage backends for blueking PaaS platform
License: MIT
Author: blueking
Author-email: blueking@tencent.com
Requires-Python: >=3.8,<3.12
Classifier: Framework :: Django
Classifier: License :: OSI Approved :: MIT License
Classifier: Programming Language :: Python :: 3
Classifier: Programming Language :: Python :: 3.8
Classifier: Programming Language :: Python :: 3.9
Classifier: Programming Language :: Python :: 3.10
Classifier: Programming Language :: Python :: 3.11
Requires-Dist: boto3 (>=1.4.1)
Requires-Dist: curlify (>=2.2.1)
Requires-Dist: django (>=4.2,<5.0)
Requires-Dist: requests
Requires-Dist: six
Project-URL: Homepage, https://github.com/TencentBlueKing/bkpaas-python-sdk/
Project-URL: Repository, https://github.com/TencentBlueKing/bkpaas-python-sdk/
